{
  "baked_count": 10,
  "laps": [
    {
      "id": "ham_2018_monza_q",
      "year": 2018,
      "race": "Italian Grand Prix",
      "track": "Monza",
      "session": "Q",
      "driver_code": "HAM",
      "driver_name": "LEWIS HAMILTON",
      "team": "MERCEDES",
      "team_color": "#00D2BE",
      "accent": "#3fc9ff",
      "era": "HYBRID  \u00b7  V6 1.6L",
      "lap_time_str": "1:19.294",
      "lap_time_ms": 79294,
      "compound": "SUPERSOFT",
      "samples": 595
    },
    {
      "id": "ham_2020_silverstone_q",
      "year": 2020,
      "race": "British Grand Prix",
      "track": "Silverstone",
      "session": "Q",
      "driver_code": "HAM",
      "driver_name": "LEWIS HAMILTON",
      "team": "MERCEDES",
      "team_color": "#00D2BE",
      "accent": "#00e8ff",
      "era": "HYBRID  \u00b7  V6 1.6L",
      "lap_time_str": "1:24.303",
      "lap_time_ms": 84303,
      "compound": "SOFT",
      "samples": 733
    },
    {
      "id": "ver_2023_silverstone_q",
      "year": 2023,
      "race": "British Grand Prix",
      "track": "Silverstone",
      "session": "Q",
      "driver_code": "VER",
      "driver_name": "MAX VERSTAPPEN",
      "team": "RED BULL RACING",
      "team_color": "#3671C6",
      "accent": "#ff4a3a",
      "era": "GROUND EFFECT  \u00b7  RB19",
      "lap_time_str": "1:26.720",
      "lap_time_ms": 86720,
      "compound": "SOFT",
      "samples": 674
    },
    {
      "id": "nor_2024_zandvoort_q",
      "year": 2024,
      "race": "Dutch Grand Prix",
      "track": "Zandvoort",
      "session": "Q",
      "driver_code": "NOR",
      "driver_name": "LANDO NORRIS",
      "team": "MCLAREN",
      "team_color": "#FF8000",
      "accent": "#ff8700",
      "era": "GROUND EFFECT  \u00b7  MCL38",
      "lap_time_str": "1:09.673",
      "lap_time_ms": 69673,
      "compound": "SOFT",
      "samples": 530
    },
    {
      "id": "lec_2024_monaco_q",
      "year": 2024,
      "race": "Monaco Grand Prix",
      "track": "Monaco",
      "session": "Q",
      "driver_code": "LEC",
      "driver_name": "CHARLES LECLERC",
      "team": "FERRARI",
      "team_color": "#E80020",
      "accent": "#ffb84a",
      "era": "GROUND EFFECT  \u00b7  SF-24",
      "lap_time_str": "1:10.270",
      "lap_time_ms": 70270,
      "compound": "SOFT",
      "samples": 537
    },
    {
      "id": "lec_2024_monza_q",
      "year": 2024,
      "race": "Italian Grand Prix",
      "track": "Monza",
      "session": "Q",
      "driver_code": "LEC",
      "driver_name": "CHARLES LECLERC",
      "team": "FERRARI",
      "team_color": "#E80020",
      "accent": "#dc0000",
      "era": "GROUND EFFECT  \u00b7  SF-24",
      "lap_time_str": "1:19.461",
      "lap_time_ms": 79461,
      "compound": "SOFT",
      "samples": 619
    },
    {
      "id": "rus_2024_silverstone_q",
      "year": 2024,
      "race": "British Grand Prix",
      "track": "Silverstone",
      "session": "Q",
      "driver_code": "RUS",
      "driver_name": "GEORGE RUSSELL",
      "team": "MERCEDES",
      "team_color": "#27F4D2",
      "accent": "#7bf2b8",
      "era": "GROUND EFFECT  \u00b7  W15",
      "lap_time_str": "1:25.819",
      "lap_time_ms": 85819,
      "compound": "SOFT",
      "samples": 645
    },
    {
      "id": "ham_2024_lasvegas_q",
      "year": 2024,
      "race": "Las Vegas Grand Prix",
      "track": "Las Vegas",
      "session": "Q",
      "driver_code": "HAM",
      "driver_name": "LEWIS HAMILTON",
      "team": "MERCEDES",
      "team_color": "#27F4D2",
      "accent": "#27f4d2",
      "era": "GROUND EFFECT  \u00b7  W15",
      "lap_time_str": "1:32.567",
      "lap_time_ms": 92567,
      "compound": "SOFT",
      "samples": 718
    },
    {
      "id": "pia_2025_australia_q",
      "year": 2025,
      "race": "Australian Grand Prix",
      "track": "Albert Park",
      "session": "Q",
      "driver_code": "PIA",
      "driver_name": "OSCAR PIASTRI",
      "team": "MCLAREN",
      "team_color": "#FF8000",
      "accent": "#ffc24d",
      "era": "GROUND EFFECT  \u00b7  MCL39",
      "lap_time_str": "1:15.180",
      "lap_time_ms": 75180,
      "compound": "SOFT",
      "samples": 566
    },
    {
      "id": "ver_2025_silverstone_q",
      "year": 2025,
      "race": "British Grand Prix",
      "track": "Silverstone",
      "session": "Q",
      "driver_code": "VER",
      "driver_name": "MAX VERSTAPPEN",
      "team": "RED BULL RACING",
      "team_color": "#4781D7",
      "accent": "#ff1801",
      "era": "GROUND EFFECT  \u00b7  RB21",
      "lap_time_str": "1:24.892",
      "lap_time_ms": 84892,
      "compound": "SOFT",
      "samples": 637
    }
  ]
}